__tests__/__init__.py
__tests__/test_graph.py
__tests__/test_simple_graph.py
py_graph_t/CompleteGraph.py
py_graph_t/Graph.py
py_graph_t/SimpleGraph.py
py_graph_t/__init__.py
py_graph_t/edges/SimpleEdge.py
py_graph_t/edges/__init__.py
py_graph_t/exceptions/SimpleGraphException.py
py_graph_t/exceptions/__init__.py
py_graph_t/util/ValueBinding.py
py_graph_t/util/__init__.py
py_graph_t/vertex/SimpleVertex.py
py_graph_t/vertex/__init__.py
PyGraphT-0.1.0.dist-info/LICENSE
PyGraphT-0.1.0.dist-info/METADATA
PyGraphT-0.1.0.dist-info/WHEEL
PyGraphT-0.1.0.dist-info/top_level.txt
PyGraphT-0.1.0.dist-info/RECORD
