Metadata-Version: 2.1
Name: PyGraphT
Version: 0.1.0
Summary: Biblioteca com intuito de implementar os grafos e seus         algoritmos de Teoria dos Grafos.
Home-page: https://github.com/Rickecr/PyGraph
Author: Rich Elton
Author-email: richelton14@gmail.com
License: MIT
Project-URL: Código fonte, https://github.com/Rickecr/PyGraph
Keywords: graph theory algorithms
Platform: UNKNOWN
